redturtle.unitaterritoriali-1.0.1-py3.11-nspkg.pth
redturtle/unitaterritoriali/__init__.py
redturtle/unitaterritoriali/codici_statistici_22_01_2024.csv
redturtle/unitaterritoriali/configure.zcml
redturtle/unitaterritoriali/interfaces.py
redturtle/unitaterritoriali/testing.py
redturtle/unitaterritoriali/utility.py
redturtle/unitaterritoriali/tests/__init__.py
redturtle/unitaterritoriali/tests/test_robot.py
redturtle/unitaterritoriali/tests/test_setup.py
redturtle/unitaterritoriali/tests/test_utility.py
redturtle/unitaterritoriali/tests/robot/test_example.robot
redturtle.unitaterritoriali-1.0.1.dist-info/LICENSE.GPL
redturtle.unitaterritoriali-1.0.1.dist-info/LICENSE.rst
redturtle.unitaterritoriali-1.0.1.dist-info/METADATA
redturtle.unitaterritoriali-1.0.1.dist-info/WHEEL
redturtle.unitaterritoriali-1.0.1.dist-info/entry_points.txt
redturtle.unitaterritoriali-1.0.1.dist-info/namespace_packages.txt
redturtle.unitaterritoriali-1.0.1.dist-info/top_level.txt
redturtle.unitaterritoriali-1.0.1.dist-info/RECORD
