Metadata-Version: 2.1
Name: redturtle.unitaterritoriali
Version: 1.0.1
Summary: An add-on for Plone
Home-page: https://github.com/RedTurtle/redturtle.unitaterritoriali
Author: Redturtle
Author-email: sviluppo@redturtle.it
License: GPL version 2
Project-URL: PyPI, https://pypi.org/project/redturtle.unitaterritoriali/
Project-URL: Source, https://github.com/RedTurtle/redturtle.unitaterritoriali
Project-URL: Tracker, https://github.com/RedTurtle/redturtle.unitaterritoriali/issues
Keywords: Python Plone CMS
Classifier: Development Status :: 5 - Production/Stable
Classifier: Environment :: Web Environment
Classifier: Framework :: Plone
Classifier: Framework :: Plone :: Addon
Classifier: Framework :: Plone :: 5.2
Classifier: Framework :: Plone :: 6.0
Classifier: Programming Language :: Python
Classifier: Programming Language :: Python :: 3.10
Classifier: Programming Language :: Python :: 3.11
Classifier: Programming Language :: Python :: 3.12
Classifier: Operating System :: OS Independent
Classifier: License :: OSI Approved :: GNU General Public License v2 (GPLv2)
Requires-Python: >=3.7
License-File: LICENSE.GPL
License-File: LICENSE.rst
Requires-Dist: setuptools
Requires-Dist: z3c.jbot
Requires-Dist: plone.api >=1.8.4
Requires-Dist: plone.app.dexterity
Provides-Extra: test
Requires-Dist: plone.app.testing ; extra == 'test'
Requires-Dist: plone.testing >=5.0.0 ; extra == 'test'
Requires-Dist: plone.app.contenttypes ; extra == 'test'
Requires-Dist: plone.app.robotframework[debug] ; extra == 'test'
